hmd_uiautomator2-0.0.18.data/data/uiautomator2/assets/app-uiautomator-test.apk
hmd_uiautomator2-0.0.18.data/data/uiautomator2/assets/app-uiautomator.apk
hmd_uiautomator2-0.0.18.data/data/uiautomator2/assets/sync.sh
hmd_uiautomator2-0.0.18.data/data/uiautomator2/ext/htmlreport/assets/index.html
hmd_uiautomator2-0.0.18.data/data/uiautomator2/ext/htmlreport/assets/pig.jpg
hmd_uiautomator2-0.0.18.data/data/uiautomator2/ext/htmlreport/assets/simplehttpserver.py
hmd_uiautomator2-0.0.18.data/data/uiautomator2/ext/htmlreport/assets/start.bat
hmd_uiautomator2-0.0.18.data/data/uiautomator2/ext-archived/aircv/README.md
hmd_uiautomator2-0.0.18.data/data/uiautomator2/ext-archived/aircv/__init__.py
hmd_uiautomator2-0.0.18.data/data/uiautomator2/ext-archived/ocr/README.md
hmd_uiautomator2-0.0.18.data/data/uiautomator2/ext-archived/ocr/__init__.py
hmd_uiautomator2-0.0.18.data/data/uiautomator2/ext-archived/ocr/baiduOCR.py
uiautomator2/__init__.py
uiautomator2/__main__.py
uiautomator2/_proto.py
uiautomator2/_selector.py
uiautomator2/abcd.py
uiautomator2/exceptions.py
uiautomator2/image.py
uiautomator2/init.py
uiautomator2/messagebox.py
uiautomator2/screenrecord.py
uiautomator2/settings.py
uiautomator2/swipe.py
uiautomator2/utils.py
uiautomator2/version.py
uiautomator2/watcher.py
uiautomator2/webview.py
uiautomator2/widget.py
uiautomator2/xpath.py
uiautomator2/assets/app-uiautomator-test.apk
uiautomator2/assets/app-uiautomator.apk
uiautomator2/assets/sync.sh
uiautomator2/ext/__init__.py
uiautomator2/ext/htmlreport/README.md
uiautomator2/ext/htmlreport/__init__.py
uiautomator2/ext/htmlreport/assets/index.html
uiautomator2/ext/htmlreport/assets/pig.jpg
uiautomator2/ext/htmlreport/assets/simplehttpserver.py
uiautomator2/ext/htmlreport/assets/start.bat
uiautomator2/ext/info/__init__.py
uiautomator2/ext/info/conf.py
uiautomator2/ext/perf/README.md
uiautomator2/ext/perf/__init__.py
uiautomator2/ext/perf/net.png
uiautomator2/ext/perf/summary.png
uiautomator2/ext/xpath/README.md
hmd_uiautomator2-0.0.18.dist-info/AUTHORS
hmd_uiautomator2-0.0.18.dist-info/LICENSE
hmd_uiautomator2-0.0.18.dist-info/METADATA
hmd_uiautomator2-0.0.18.dist-info/WHEEL
hmd_uiautomator2-0.0.18.dist-info/entry_points.txt
hmd_uiautomator2-0.0.18.dist-info/pbr.json
hmd_uiautomator2-0.0.18.dist-info/top_level.txt
hmd_uiautomator2-0.0.18.dist-info/RECORD
